hubmap_mudata_validator-1.0.7.dist-info/licenses/LICENSE
mudata_validator/__init__.py
mudata_validator/validator.py
tests/__init__.py
tests/test_validator.py
hubmap_mudata_validator-1.0.7.dist-info/METADATA
hubmap_mudata_validator-1.0.7.dist-info/WHEEL
hubmap_mudata_validator-1.0.7.dist-info/top_level.txt
hubmap_mudata_validator-1.0.7.dist-info/RECORD
